verilog/gpu/sync_generator.v
module sync_generator (
    input pixel_clk, 
    input rst,

    output reg [9:0] cycle,
    output reg [8:0] scanline,
    output vga_hs,
    output vga_vs,
    output reg vga_blank
);

always @ (posedge pixel_clk or negedge rst) begin
    if (rst == 1'b0) begin
        cycle = 0;
        scanline = 0;
    end else begin
        cycle = cycle + 1'b1;

        if (cycle == 800) begin
            cycle = 0;
            scanline = scanline + 1;

            if (scanline == 525) begin
                scanline = 0;
            end
        end
    
        if (cycle >= 640 || scanline >= 480) begin
            vga_blank <= 1'b1;
        end else begin
            vga_blank <= 1'b0;
        end
    end
end

assign vga_hs = cycle >= (640 + 16) && cycle <= (640 + 16 + 96);
assign vga_vs = scanline >= (480 + 10) && scanline <= (480 + 10 + 2); 

endmodule

verilog/gpu/sync_generator_tb.v
`default_nettype none
`define DUMPSTR(x) `"x.vcd`"
`timescale 1ps / 10fs

module sync_generator_tb();

parameter DURATION = 10000000;

reg pixel_clk = 0;
reg rst = 0;
always #1 pixel_clk = ~pixel_clk;

wire [9:0] cycle;
wire [8:0] scanline;
wire vga_hs;
wire vga_vs;
wire vga_blank;

sync_generator uut (
    .pixel_clk(pixel_clk),
    .rst(rst),

    .cycle(cycle),
    .scanline(scanline),
    .vga_hs(vga_hs),
    .vga_vs(vga_vs),
    .vga_blank(vga_blank)
);

initial begin
    #0.1
    rst = 1'b0;
    #1
    rst = 1'b1;
end

initial begin
  $dumpfile(`DUMPSTR(`VCD_OUTPUT));
  $dumpvars(0, sync_generator_tb);

   #(DURATION) $display("End of simulation");
  $finish;
end

endmodule

verilog/gpu/pixel_generator.v
module pixel_generator (
    input rst,
    input pixel_clk,
    input clk,
    input [9:0] cycle,
    input [8:0] scanline,
    input [7:0] tile_memory_read_data,
    input [7:0] attribute_memory_read_data,
    input [7:0] color_memory_read_data,

    output reg [10:0] tile_memory_read_addr,
    output reg tile_memory_read_enable,
    output reg [11:0] attribute_memory_read_addr,
    output reg attribute_memory_read_enable,
    output reg [3:0] color_memory_read_addr,
    output reg color_memory_read_enable,
    output [7:0] pixel_data
);

reg gottenPixelClock;

reg [1:0] step;
reg [7:0] tileNumber;
reg [7:0] tileData;
reg [7:0] colorAttribute;
reg pixelOn;
reg [7:0] color;

reg [9:0] offsetCycle;
reg [8:0] offsetScanline;

reg [5:0] charColumn;
reg [4:0] charRow;

reg [2:0] charRenderColumn;
reg [2:0] charRenderRow;

// There will be 3 clk between each pixel_clk, use these clock cycles to fetch stuff from RAM
always @ (posedge clk or negedge rst) begin
    if(rst == 0) begin
        gottenPixelClock <= 0;
        step <= 0;
        pixelOn <= 0;
        color <= 0;
        offsetCycle <= 0;
        offsetScanline <= 0;
        charColumn <= 0;
        charRow <= 0;
        charRenderColumn <= 0;
        charRenderRow <= 0;
        tile_memory_read_addr <= 0;
        tileNumber <= 0;
        tileData <= 0;
        colorAttribute <= 0;
        tile_memory_read_enable <= 0;
    end else begin
        offsetCycle <= cycle[9:1] + 0;
        offsetScanline <= scanline[8:1] + 0;

        if(gottenPixelClock == 1 || pixel_clk == 1) begin
            gottenPixelClock = 1;

            case (step)
                0: begin
                    charColumn = offsetCycle >> 3; 
                    charRow = offsetScanline >> 3;

                    charRenderColumn = offsetCycle & 3'h7;
                    charRenderRow = offsetScanline & 3'h7;

                    tile_memory_read_addr = {charRow, charColumn};
                    tile_memory_read_enable = 1;

                    attribute_memory_read_addr = {1'b0, charRow, charColumn};
                    attribute_memory_read_enable = 1;
                    step = step + 1;
                end 
                1: begin
                    tileNumber = tile_memory_read_data;
                    colorAttribute = attribute_memory_read_data;

                    attribute_memory_read_addr = {1'b1, tileNumber, charRenderRow};
                    attribute_memory_read_enable = 1;
                    step = step + 1;
                end
                2: begin
                    tileData = attribute_memory_read_data;
                    pixelOn = (tileData >> charRenderColumn) & 1;

                    color_memory_read_addr = pixelOn == 1 ? colorAttribute[7:4] : colorAttribute[3:0];
                    color_memory_read_enable = 1;

                    step = 0;
                end
            endcase
        end
    end
end

assign pixel_data =  /* pixel_clk == 1 ? */ color_memory_read_data /* : 0 */;

endmodule

verilog/gpu/memory.v
module memory #(
     parameter  INIT_FILE = "",
     parameter  ADDRESS_WIDTH = 10,
     parameter  DATA_WIDTH = 8
) (
    input clk,
    input [ADDRESS_WIDTH - 1:0] read_addr,
    input read_enable,
    
    input [ADDRESS_WIDTH - 1:0] write_addr,
    input write_enable,
    input [DATA_WIDTH - 1:0] write_data, 

    output reg [DATA_WIDTH - 1:0] read_data
);

    reg [7:0] mem [0:(2**ADDRESS_WIDTH + 1) - 1];
    
    // Interact with the memory block
    always @ (posedge clk) begin
    
        // Write to memory
        if (write_enable == 1'b1) begin
            mem[write_addr] <= write_data;
        end
        
        // Read from memory
        if(read_enable == 1'b1) begin
            read_data <= mem[read_addr];
        end
    end

    initial if (INIT_FILE) begin
        $readmemh(INIT_FILE, mem);
    end

endmodule

verilog/gpu/clock_divider.v
module clock_divider #(
  parameter DIVISON = 2,
  parameter DIVISION_WIDTH = 2
)(
    input clk,
    input rst,

    output reg tick
);

reg [DIVISION_WIDTH:0] count;

always @(posedge clk or negedge rst) begin
    if (rst == 0) begin
        count <= 1'b0;
        tick <= 1'b0;
    end else if (count == DIVISON - 1) begin
        count <= 1'b0;
        tick <= ~tick;
    end else begin
        count <= count + 1'b1; 
    end
end

endmodule

verilog/gpu/pixel_generator_tb.v
`default_nettype none
`define DUMPSTR(x) `"x.vcd`"
`timescale 1ns / 10ps

module pixel_generator_tb();

wire pixel_clk;
reg CLK100MHz = 1;
reg rst = 0;
wire [7:0] pixel_data;

reg [9:0] cycle;
reg [8:0] scanline;

wire tile_memory_read_enable;
wire [10:0] tile_memory_read_addr;
wire [7:0] tile_memory_read_data;

wire attribute_memory_read_enable;
wire [11:0] attribute_memory_read_addr;
wire [7:0] attribute_memory_read_data;

wire color_memory_read_enable;
wire [3:0] color_memory_read_addr;
wire [7:0] color_memory_read_data;

clock_divider #(.DIVISON(2)) vga_div (
    .clk(CLK100MHz),
    .rst(rst),
    .tick(pixel_clk)
);

memory #(
    .ADDRESS_WIDTH(11),
    .INIT_FILE("tile_mem.txt")
) tile_memory (
    .clk(CLK100MHz),
    .read_enable(tile_memory_read_enable),
    .read_addr(tile_memory_read_addr),
    .read_data(tile_memory_read_data),

    .write_enable(1'b0),
    .write_data(8'd0),
    .write_addr(11'b0)
);

memory #(
    .ADDRESS_WIDTH(12),
    .INIT_FILE("attribute_mem.txt")
) attribute_memory (
    .clk(CLK100MHz),
    .read_enable(attribute_memory_read_enable),
    .read_addr(attribute_memory_read_addr),
    .read_data(attribute_memory_read_data),

    .write_enable(1'b0),
    .write_data(8'd0),
    .write_addr(12'b0)
);

memory #(
    .ADDRESS_WIDTH(4),
    .INIT_FILE("color_mem.txt")
) color_memory (
    .clk(CLK100MHz),
    .read_enable(color_memory_read_enable),
    .read_addr(color_memory_read_addr),
    .read_data(color_memory_read_data),

    .write_enable(1'b0),
    .write_data(8'd0),
    .write_addr(4'b0)
);


pixel_generator uut (
    .rst(rst),
    .pixel_clk(pixel_clk),
    .clk(CLK100MHz),
    .cycle(cycle),
    .scanline(scanline),

    .tile_memory_read_enable(tile_memory_read_enable),
    .tile_memory_read_addr(tile_memory_read_addr),
    .tile_memory_read_data(tile_memory_read_data),

    .attribute_memory_read_enable(attribute_memory_read_enable),
    .attribute_memory_read_addr(attribute_memory_read_addr),
    .attribute_memory_read_data(attribute_memory_read_data),

    .color_memory_read_enable(color_memory_read_enable),
    .color_memory_read_addr(color_memory_read_addr),
    .color_memory_read_data(color_memory_read_data),

    .pixel_data(pixel_data)
);

initial begin
$dumpfile(`DUMPSTR(`VCD_OUTPUT));
    $dumpvars(0, pixel_generator_tb);

    #1 CLK100MHz = ~CLK100MHz;     #1 CLK100MHz = ~CLK100MHz; 
    rst = 1'b0;
    #1 CLK100MHz = ~CLK100MHz;     #1 CLK100MHz = ~CLK100MHz; 
    rst = 1'b1;

    cycle = 19;
    scanline = 1;

    #1 CLK100MHz = ~CLK100MHz;     #1 CLK100MHz = ~CLK100MHz;
    #1 CLK100MHz = ~CLK100MHz;     #1 CLK100MHz = ~CLK100MHz;
    #1 CLK100MHz = ~CLK100MHz;     #1 CLK100MHz = ~CLK100MHz;
    #1 CLK100MHz = ~CLK100MHz;     #1 CLK100MHz = ~CLK100MHz;

    cycle = 20;
    scanline = 2;

    #1 CLK100MHz = ~CLK100MHz;     #1 CLK100MHz = ~CLK100MHz;
    #1 CLK100MHz = ~CLK100MHz;     #1 CLK100MHz = ~CLK100MHz;
    #1 CLK100MHz = ~CLK100MHz;     #1 CLK100MHz = ~CLK100MHz;
    #1 CLK100MHz = ~CLK100MHz;     #1 CLK100MHz = ~CLK100MHz;

    #1 CLK100MHz = ~CLK100MHz;     #1 CLK100MHz = ~CLK100MHz;
    #1 CLK100MHz = ~CLK100MHz;     #1 CLK100MHz = ~CLK100MHz;
    #1 CLK100MHz = ~CLK100MHz;     #1 CLK100MHz = ~CLK100MHz;
    #1 CLK100MHz = ~CLK100MHz;     #1 CLK100MHz = ~CLK100MHz;

    $display("End of simulation");
    $finish;
end

endmodule

verilog/gpu/gpu.v
module gpu (
    input CLK100MHz,
    input rst,
    input [7:0] data,
    input [3:0] addr,
    input rw,
    input cs_clock,

    output wire vga_hs,
    output wire vga_vs,
    output wire [2:0] vga_r,
    output wire [2:0] vga_g,
    output wire [2:0] vga_b,
    output wire irq
);

wire pixel_clk;
wire vga_blank;
wire [9:0] cycle;
wire [8:0] scanline;
wire [7:0] pixel_data;

wire tile_memory_read_enable;
wire [10:0] tile_memory_read_addr;
wire [7:0] tile_memory_read_data;

wire attribute_memory_read_enable;
wire [11:0] attribute_memory_read_addr;
wire [7:0] attribute_memory_read_data;

wire color_memory_read_enable;
wire [3:0] color_memory_read_addr;
wire [7:0] color_memory_read_data;

memory #(
    .ADDRESS_WIDTH(11),
    .INIT_FILE("tile_mem.txt")
) tile_memory (
    .clk(CLK100MHz),
    .read_enable(tile_memory_read_enable),
    .read_addr(tile_memory_read_addr),
    .read_data(tile_memory_read_data),

    .write_enable(1'b0),
    .write_data(8'd0),
    .write_addr(11'b0)
);

memory #(
    .ADDRESS_WIDTH(12),
    .INIT_FILE("attribute_mem.txt")
) attribute_memory (
    .clk(CLK100MHz),
    .read_enable(attribute_memory_read_enable),
    .read_addr(attribute_memory_read_addr),
    .read_data(attribute_memory_read_data),

    .write_enable(1'b0),
    .write_data(8'd0),
    .write_addr(12'b0)
);

memory #(
    .ADDRESS_WIDTH(4),
    .INIT_FILE("color_mem.txt")
) color_memory (
    .clk(CLK100MHz),
    .read_enable(color_memory_read_enable),
    .read_addr(color_memory_read_addr),
    .read_data(color_memory_read_data),

    .write_enable(1'b0),
    .write_data(8'd0),
    .write_addr(4'b0)
);


clock_divider #(.DIVISON(2)) vga_div (
    .clk(CLK100MHz),
    .rst(rst),
    .tick(pixel_clk)
);

sync_generator sync_gen (
    .pixel_clk(pixel_clk),
    .rst(rst),

    .cycle(cycle),
    .scanline(scanline),
    .vga_hs(vga_hs),
    .vga_vs(vga_vs),
    .vga_blank(vga_blank)
);

pixel_generator pixel_gen (
    .rst(rst),
    .pixel_clk(pixel_clk),
    .clk(CLK100MHz),
    .cycle(cycle),
    .scanline(scanline),

    .tile_memory_read_enable(tile_memory_read_enable),
    .tile_memory_read_addr(tile_memory_read_addr),
    .tile_memory_read_data(tile_memory_read_data),

    .attribute_memory_read_enable(attribute_memory_read_enable),
    .attribute_memory_read_addr(attribute_memory_read_addr),
    .attribute_memory_read_data(attribute_memory_read_data),

    .color_memory_read_enable(color_memory_read_enable),
    .color_memory_read_addr(color_memory_read_addr),
    .color_memory_read_data(color_memory_read_data),

    .pixel_data(pixel_data)
);

assign vga_r = (vga_blank == 1) ? 0 : pixel_data[2:0]; 
assign vga_g = (vga_blank == 1) ? 0 : pixel_data[4:2]; 
assign vga_b = (vga_blank == 1) ? 0 : pixel_data[7:5]; 

endmodule

verilog/gpu/gpu_tb.v
`default_nettype none
`define DUMPSTR(x) `"x.vcd`"
`timescale 1ps / 10fs

module gpu_tb();

parameter DURATION = 10000000;

reg CLK100MHz = 0;
reg rst = 0;
always #1 CLK100MHz = ~CLK100MHz;

wire [7:0] data = 0;
wire [3:0] addr = 0;
wire rw = 0;
wire cs_clock = 1;

wire [2:0] vga_r;
wire [2:0] vga_g;
wire [2:0] vga_b;
wire irq;
wire vga_hs;
wire vga_vs;

gpu uut (
    .CLK100MHz(CLK100MHz),
    .rst(rst),
    .data(data),
    .addr(addr),
    .rw(rw),
    .cs_clock(cs_clock),

    .vga_hs(vga_hs),
    .vga_vs(vga_vs),
    .vga_r(vga_r),
    .vga_g(vga_g),
    .vga_b(vga_b),
    .irq(irq)
);

initial begin
    #0.1
    rst = 1'b0;
    #1
    rst = 1'b1;
end

initial begin
  $dumpfile(`DUMPSTR(`VCD_OUTPUT));
  $dumpvars(0, gpu_tb);

   #(DURATION) $display("End of simulation");
  $finish;
end

endmodule

verilog/gpu/clock_divider_tb.v
`default_nettype none
`define DUMPSTR(x) `"x.vcd`"
`timescale 100 ns / 10 ns

module clock_divider_tb();

parameter DURATION = 20;

reg clk = 0;
reg rst = 0;
always #0.5 clk = ~clk;

wire pixel_clk;

clock_divider #(.DIVISON(4), .DIVISION_WIDTH(3)) uut (
    .clk(clk),
    .rst(rst),
    .tick(pixel_clk)
);

initial begin
    #0.1
    rst = 1'b0;
    #1
    rst = 1'b1;
end

initial begin
  $dumpfile(`DUMPSTR(`VCD_OUTPUT));
  $dumpvars(0, clock_divider_tb);

   #(DURATION) $display("End of simulation");
  $finish;
end

endmodule

verilog/gpu/clock_divider_tb.vcd
$date
	Thu Jan  5 19:10:48 2023
$end
$version
	Icarus Verilog
$end
$timescale
	10fs
$end
$scope module clock_divider_tb $end
$var wire 1 ! pixel_clk $end
$var reg 1 " clk $end
$var reg 1 # rst $end
$scope module uut $end
$var wire 1 " clk $end
$var wire 1 # rst $end
$var reg 4 $ count [3:0] $end
$var reg 1 ! tick $end
$upscope $end
$upscope $end
$scope module gpu_tb $end
$var wire 4 % addr [3:0] $end
$var wire 1 & cs_clock $end
$var wire 8 ' data [7:0] $end
$var wire 1 ( irq $end
$var wire 1 ) rw $end
$var wire 1 * vga_vs $end
$var wire 3 + vga_r [2:0] $end
$var wire 1 , vga_hs $end
$var wire 3 - vga_g [2:0] $end
$var wire 3 . vga_b [2:0] $end
$var reg 1 / CLK100MHz $end
$var reg 1 0 rst $end
$scope module uut $end
$var wire 1 / CLK100MHz $end
$var wire 4 1 addr [3:0] $end
$var wire 1 & cs_clock $end
$var wire 8 2 data [7:0] $end
$var wire 1 ( irq $end
$var wire 1 0 rst $end
$var wire 1 ) rw $end
$var wire 1 * vga_vs $end
$var wire 3 3 vga_r [2:0] $end
$var wire 1 , vga_hs $end
$var wire 3 4 vga_g [2:0] $end
$var wire 1 5 vga_blank $end
$var wire 3 6 vga_b [2:0] $end
$var wire 1 7 tile_memory_read_enable $end
$var wire 8 8 tile_memory_read_data [7:0] $end
$var wire 11 9 tile_memory_read_addr [10:0] $end
$var wire 9 : scanline [8:0] $end
$var wire 8 ; pixel_data [7:0] $end
$var wire 1 < pixel_clk $end
$var wire 10 = cycle [9:0] $end
$var wire 1 > color_memory_read_enable $end
$var wire 8 ? color_memory_read_data [7:0] $end
$var wire 4 @ color_memory_read_addr [3:0] $end
$var wire 1 A attribute_memory_read_enable $end
$var wire 8 B attribute_memory_read_data [7:0] $end
$var wire 12 C attribute_memory_read_addr [11:0] $end
$scope module attribute_memory $end
$var wire 1 / clk $end
$var wire 12 D write_addr [11:0] $end
$var wire 8 E write_data [7:0] $end
$var wire 1 F write_enable $end
$var wire 1 A read_enable $end
$var wire 12 G read_addr [11:0] $end
$var reg 8 H read_data [7:0] $end
$upscope $end
$scope module color_memory $end
$var wire 1 / clk $end
$var wire 4 I write_addr [3:0] $end
$var wire 8 J write_data [7:0] $end
$var wire 1 K write_enable $end
$var wire 1 > read_enable $end
$var wire 4 L read_addr [3:0] $end
$var reg 8 M read_data [7:0] $end
$upscope $end
$scope module pixel_gen $end
$var wire 8 N attribute_memory_read_data [7:0] $end
$var wire 1 / clk $end
$var wire 8 O color_memory_read_data [7:0] $end
$var wire 1 0 rst $end
$var wire 8 P tile_memory_read_data [7:0] $end
$var wire 9 Q scanline [8:0] $end
$var wire 8 R pixel_data [7:0] $end
$var wire 1 < pixel_clk $end
$var wire 10 S cycle [9:0] $end
$var reg 12 T attribute_memory_read_addr [11:0] $end
$var reg 1 A attribute_memory_read_enable $end
$var reg 6 U charColumn [5:0] $end
$var reg 3 V charRenderColumn [2:0] $end
$var reg 3 W charRenderRow [2:0] $end
$var reg 5 X charRow [4:0] $end
$var reg 8 Y color [7:0] $end
$var reg 8 Z colorAttribute [7:0] $end
$var reg 4 [ color_memory_read_addr [3:0] $end
$var reg 1 > color_memory_read_enable $end
$var reg 1 \ gottenPixelClock $end
$var reg 10 ] offsetCycle [9:0] $end
$var reg 9 ^ offsetScanline [8:0] $end
$var reg 1 _ pixelOn $end
$var reg 2 ` step [1:0] $end
$var reg 8 a tileData [7:0] $end
$var reg 8 b tileNumber [7:0] $end
$var reg 11 c tile_memory_read_addr [10:0] $end
$var reg 1 7 tile_memory_read_enable $end
$upscope $end
$scope module sync_gen $end
$var wire 1 0 rst $end
$var wire 1 , vga_hs $end
$var wire 1 * vga_vs $end
$var wire 1 < pixel_clk $end
$var reg 10 d cycle [9:0] $end
$var reg 9 e scanline [8:0] $end
$var reg 1 5 vga_blank $end
$upscope $end
$scope module tile_memory $end
$var wire 1 / clk $end
$var wire 11 f read_addr [10:0] $end
$var wire 1 7 read_enable $end
$var wire 11 g write_addr [10:0] $end
$var wire 8 h write_data [7:0] $end
$var wire 1 i write_enable $end
$var reg 8 j read_data [7:0] $end
$upscope $end
$scope module vga_div $end
$var wire 1 / clk $end
$var wire 1 0 rst $end
$var reg 3 k count [2:0] $end
$var reg 1 < tick $end
$upscope $end
$upscope $end
$upscope $end
$scope module pixel_generator_tb $end
$var wire 1 l tile_memory_read_enable $end
$var wire 8 m tile_memory_read_data [7:0] $end
$var wire 11 n tile_memory_read_addr [10:0] $end
$var wire 8 o pixel_data [7:0] $end
$var wire 1 p pixel_clk $end
$var wire 1 q color_memory_read_enable $end
$var wire 8 r color_memory_read_data [7:0] $end
$var wire 4 s color_memory_read_addr [3:0] $end
$var wire 1 t attribute_memory_read_enable $end
$var wire 8 u attribute_memory_read_data [7:0] $end
$var wire 12 v attribute_memory_read_addr [11:0] $end
$var reg 1 w CLK100MHz $end
$var reg 10 x cycle [9:0] $end
$var reg 1 y rst $end
$var reg 9 z scanline [8:0] $end
$scope module attribute_memory $end
$var wire 1 w clk $end
$var wire 12 { write_addr [11:0] $end
$var wire 8 | write_data [7:0] $end
$var wire 1 } write_enable $end
$var wire 1 t read_enable $end
$var wire 12 ~ read_addr [11:0] $end
$var reg 8 !" read_data [7:0] $end
$upscope $end
$scope module color_memory $end
$var wire 1 w clk $end
$var wire 4 "" write_addr [3:0] $end
$var wire 8 #" write_data [7:0] $end
$var wire 1 $" write_enable $end
$var wire 1 q read_enable $end
$var wire 4 %" read_addr [3:0] $end
$var reg 8 &" read_data [7:0] $end
$upscope $end
$scope module tile_memory $end
$var wire 1 w clk $end
$var wire 11 '" write_addr [10:0] $end
$var wire 8 (" write_data [7:0] $end
$var wire 1 )" write_enable $end
$var wire 1 l read_enable $end
$var wire 11 *" read_addr [10:0] $end
$var reg 8 +" read_data [7:0] $end
$upscope $end
$scope module uut $end
$var wire 8 ," attribute_memory_read_data [7:0] $end
$var wire 1 w clk $end
$var wire 8 -" color_memory_read_data [7:0] $end
$var wire 10 ." cycle [9:0] $end
$var wire 1 y rst $end
$var wire 9 /" scanline [8:0] $end
$var wire 8 0" tile_memory_read_data [7:0] $end
$var wire 8 1" pixel_data [7:0] $end
$var wire 1 p pixel_clk $end
$var reg 12 2" attribute_memory_read_addr [11:0] $end
$var reg 1 t attribute_memory_read_enable $end
$var reg 6 3" charColumn [5:0] $end
$var reg 3 4" charRenderColumn [2:0] $end
$var reg 3 5" charRenderRow [2:0] $end
$var reg 5 6" charRow [4:0] $end
$var reg 8 7" color [7:0] $end
$var reg 8 8" colorAttribute [7:0] $end
$var reg 4 9" color_memory_read_addr [3:0] $end
$var reg 1 q color_memory_read_enable $end
$var reg 1 :" gottenPixelClock $end
$var reg 10 ;" offsetCycle [9:0] $end
$var reg 9 <" offsetScanline [8:0] $end
$var reg 1 =" pixelOn $end
$var reg 2 >" step [1:0] $end
$var reg 8 ?" tileData [7:0] $end
$var reg 8 @" tileNumber [7:0] $end
$var reg 11 A" tile_memory_read_addr [10:0] $end
$var reg 1 l tile_memory_read_enable $end
$upscope $end
$scope module vga_div $end
$var wire 1 w clk $end
$var wire 1 y rst $end
$var reg 3 B" count [2:0] $end
$var reg 1 p tick $end
$upscope $end
$upscope $end
$scope module sync_generator_tb $end
$var wire 1 C" vga_vs $end
$var wire 1 D" vga_hs $end
$var wire 1 E" vga_blank $end
$var wire 9 F" scanline [8:0] $end
$var wire 10 G" cycle [9:0] $end
$var reg 1 H" pixel_clk $end
$var reg 1 I" rst $end
$scope module uut $end
$var wire 1 H" pixel_clk $end
$var wire 1 I" rst $end
$var wire 1 D" vga_hs $end
$var wire 1 C" vga_vs $end
$var reg 10 J" cycle [9:0] $end
$var reg 9 K" scanline [8:0] $end
$var reg 1 E" vga_blank $end
$upscope $end
$upscope $end
$enddefinitions $end
#0
$dumpvars
b0 K"
b0 J"
0I"
0H"
b0 G"
b0 F"
xE"
1D"
1C"
b0 B"
b0 A"
b0 @"
b0 ?"
b0 >"
0="
b0 <"
b0 ;"
0:"
bx 9"
b0 8"
b0 7"
b0 6"
b0 5"
b0 4"
b0 3"
bx 2"
b0 1"
bx 0"
bx /"
bx ."
bx -"
bx ,"
bx +"
b0 *"
0)"
b0 ("
b0 '"
bx &"
bx %"
0$"
b0 #"
b0 ""
bx !"
bx ~
0}
b0 |
b0 {
bx z
0y
bx x
1w
bx v
bx u
xt
bx s
bx r
xq
0p
b0 o
b0 n
bx m
0l
b0 k
bx j
0i
b0 h
b0 g
b0 f
b0 e
b0 d
b0 c
b0 b
b0 a
b0 `
0_
b0 ^
b0 ]
0\
bx [
b0 Z
b0 Y
b0 X
b0 W
b0 V
b0 U
bx T
b0 S
b0 R
b0 Q
bx P
bx O
bx N
bx M
bx L
0K
b0 J
b0 I
bx H
bx G
0F
b0 E
b0 D
bx C
bx B
xA
bx @
bx ?
x>
b0 =
0<
b0 ;
b0 :
b0 9
bx 8
07
b0 6
x5
b0 4
b0 3
b0 2
b0 1
00
0/
b0 .
b0 -
1,
b0 +
1*
0)
z(
b0 '
1&
b0 %
b0 $
0#
0"
0!
$end
#100
1H"
1/
#110
1I"
10
#200
0H"
0/
#300
b1 k
0E"
b1 G"
b1 J"
1H"
1/
#400
0H"
0/
#500
bx .
bx 6
bx -
bx 4
bx +
bx 3
bx ;
bx R
05
b1 =
b1 S
b1 d
1<
b0 k
b10 G"
b10 J"
1H"
1/
#600
0H"
0/
#700
b10000 B
b10000 H
b10000 N
b1001000 8
b1001000 P
b1001000 j
b1 k
b11 G"
b11 J"
b1 `
1A
b0 C
b0 G
b0 T
17
1\
1H"
1/
#800
0H"
0/
#900
b0 .
b0 6
b0 -
b0 4
b0 +
b0 3
b0 ;
b0 R
b110011 B
b110011 H
b110011 N
0<
b0 k
b100 G"
b100 J"
b10 `
b101001000000 C
b101001000000 G
b101001000000 T
b10000 Z
b1001000 b
1H"
1/
#1000
0H"
0/
#1100
b11111111 ?
b11111111 M
b11111111 O
b1 k
b101 G"
b101 J"
b0 `
1>
b1 @
b1 L
b1 [
1_
b110011 a
1H"
1/
#1200
0H"
0/
#1300
b111 .
b111 6
b111 -
b111 4
b111 +
b111 3
b11111111 ;
b11111111 R
b10 =
b10 S
b10 d
b10000 B
b10000 H
b10000 N
1<
b0 k
b110 G"
b110 J"
b1 `
b0 C
b0 G
b0 T
1H"
1/
#1400
0H"
0/
#1500
b110011 B
b110011 H
b110011 N
b1 k
b1 ]
b111 G"
b111 J"
b10 `
b101001000000 C
b101001000000 G
b101001000000 T
1H"
1/
#1600
0H"
0/
#1700
b0 .
b0 6
b0 -
b0 4
b0 +
b0 3
b0 ;
b0 R
0<
b0 k
b1000 G"
b1000 J"
b0 `
1H"
1/
#1800
0H"
0/
#1900
b10000 B
b10000 H
b10000 N
b1 k
b1001 G"
b1001 J"
b1 `
b0 C
b0 G
b0 T
b1 V
1H"
1/
#2000
0H"
0/
#2100
b111 .
b111 6
b111 -
b111 4
b111 +
b111 3
b11111111 ;
b11111111 R
b11 =
b11 S
b11 d
b110011 B
b110011 H
b110011 N
1<
b0 k
b1010 G"
b1010 J"
b10 `
b101001000000 C
b101001000000 G
b101001000000 T
1H"
1/
#2200
0H"
0/
#2300
b1 k
b1011 G"
b1011 J"
b0 `
1H"
1/
#2400
0H"
0/
#2500
b0 .
b0 6
b0 -
b0 4
b0 +
b0 3
b0 ;
b0 R
b10000 B
b10000 H
b10000 N
0<
b0 k
b1100 G"
b1100 J"
b1 `
b0 C
b0 G
b0 T
1H"
1/
#2600
0H"
0/
#2700
b110011 B
b110011 H
b110011 N
b1 k
b1101 G"
b1101 J"
b10 `
b101001000000 C
b101001000000 G
b101001000000 T
1H"
1/
#2800
0H"
0/
#2900
b111 .
b111 6
b111 -
b111 4
b111 +
b111 3
b11111111 ;
b11111111 R
b100 =
b100 S
b100 d
1<
b0 k
b1110 G"
b1110 J"
b0 `
1H"
1/
#3000
0H"
0/
#3100
b10000 B
b10000 H
b10000 N
b1 k
b10 ]
b1111 G"
b1111 J"
b1 `
b0 C
b0 G
b0 T
1H"
1/
#3200
0H"
0/
#3300
b0 .
b0 6
b0 -
b0 4
b0 +
b0 3
b0 ;
b0 R
b110011 B
b110011 H
b110011 N
0<
b0 k
b10000 G"
b10000 J"
b10 `
b101001000000 C
b101001000000 G
b101001000000 T
1H"
1/
#3400
0H"
0/
#3500
b1 k
b10001 G"
b10001 J"
b0 `
1H"
1/
#3600
0H"
0/
#3700
b111 .
b111 6
b111 -
b111 4
b111 +
b111 3
b11111111 ;
b11111111 R
b101 =
b101 S
b101 d
b10000 B
b10000 H
b10000 N
1<
b0 k
b10010 G"
b10010 J"
b1 `
b0 C
b0 G
b0 T
b10 V
1H"
1/
#3800
0H"
0/
#3900
b110011 B
b110011 H
b110011 N
b1 k
b10011 G"
b10011 J"
b10 `
b101001000000 C
b101001000000 G
b101001000000 T
1H"
1/
#4000
0H"
0/
#4100
b0 .
b0 6
b0 -
b0 4
b0 +
b0 3
b0 ;
b0 R
b0 ?
b0 M
b0 O
0<
b0 k
b10100 G"
b10100 J"
b0 `
b0 @
b0 L
b0 [
0_
1H"
1/
#4200
0H"
0/
#4300
b10000 B
b10000 H
b10000 N
b1 k
b10101 G"
b10101 J"
b1 `
b0 C
b0 G
b0 T
1H"
1/
#4400
0H"
0/
#4500
b110 =
b110 S
b110 d
b110011 B
b110011 H
b110011 N
1<
b0 k
b10110 G"
b10110 J"
b10 `
b101001000000 C
b101001000000 G
b101001000000 T
1H"
1/
#4600
0H"
0/
#4700
b1 k
b11 ]
b10111 G"
b10111 J"
b0 `
1H"
1/
#4800
0H"
0/
#4900
b10000 B
b10000 H
b10000 N
0<
b0 k
b11000 G"
b11000 J"
b1 `
b0 C
b0 G
b0 T
b11 V
1H"
1/
#5000
0H"
0/
#5100
b110011 B
b110011 H
b110011 N
b1 k
b11001 G"
b11001 J"
b10 `
b101001000000 C
b101001000000 G
b101001000000 T
1H"
1/
#5200
0H"
0/
#5300
b111 =
b111 S
b111 d
1<
b0 k
b11010 G"
b11010 J"
b0 `
1H"
1/
#5400
0H"
0/
#5500
b10000 B
b10000 H
b10000 N
b1 k
b11011 G"
b11011 J"
b1 `
b0 C
b0 G
b0 T
1H"
1/
#5600
0H"
0/
#5700
b110011 B
b110011 H
b110011 N
0<
b0 k
b11100 G"
b11100 J"
b10 `
b101001000000 C
b101001000000 G
b101001000000 T
1H"
1/
#5800
0H"
0/
#5900
b1 k
b11101 G"
b11101 J"
b0 `
1H"
1/
#6000
0H"
0/
#6100
b1000 =
b1000 S
b1000 d
b10000 B
b10000 H
b10000 N
1<
b0 k
b11110 G"
b11110 J"
b1 `
b0 C
b0 G
b0 T
1H"
1/
#6200
0H"
0/
#6300
b110011 B
b110011 H
b110011 N
b1 k
b100 ]
b11111 G"
b11111 J"
b10 `
b101001000000 C
b101001000000 G
b101001000000 T
1H"
1/
#6400
0H"
0/
#6500
0<
b0 k
b100000 G"
b100000 J"
b0 `
1H"
1/
#6600
0H"
0/
#6700
b10000 B
b10000 H
b10000 N
b1 k
b100001 G"
b100001 J"
b1 `
b0 C
b0 G
b0 T
b100 V
1H"
1/
#6800
0H"
0/
#6900
b1001 =
b1001 S
b1001 d
b110011 B
b110011 H
b110011 N
1<
b0 k
b100010 G"
b100010 J"
b10 `
b101001000000 C
b101001000000 G
b101001000000 T
1H"
1/
#7000
0H"
0/
#7100
b111 .
b111 6
b111 -
b111 4
b111 +
b111 3
b11111111 ;
b11111111 R
b11111111 ?
b11111111 M
b11111111 O
b1 k
b100011 G"
b100011 J"
b0 `
b1 @
b1 L
b1 [
1_
1H"
1/
#7200
0H"
0/
#7300
b0 .
b0 6
b0 -
b0 4
b0 +
b0 3
b0 ;
b0 R
b10000 B
b10000 H
b10000 N
0<
b0 k
b100100 G"
b100100 J"
b1 `
b0 C
b0 G
b0 T
1H"
1/
#7400
0H"
0/
