verilog/gpu/sync_generator.v
module sync_generator (
    input pixel_clk, 
    input rst,

    output reg [9:0] cycle,
    output reg [8:0] scanline,
    output vga_hs,
    output vga_vs,
    output reg vga_blank
);

always @ (posedge pixel_clk or negedge rst) begin
    if (rst == 1'b0) begin
        cycle = 0;
        scanline = 0;
    end else begin
        cycle = cycle + 1'b1;

        if (cycle == 800) begin
            cycle = 0;
            scanline = scanline + 1;

            if (scanline == 525) begin
                scanline = 0;
            end
        end
    
        if (cycle >= 640 || scanline >= 480) begin
            vga_blank <= 1'b1;
        end else begin
            vga_blank <= 1'b0;
        end
    end
end

assign vga_hs = cycle >= (640 + 16) && cycle <= (640 + 16 + 96);
assign vga_vs = scanline >= (480 + 10) && scanline <= (480 + 10 + 2); 

endmodule

verilog/gpu/sync_generator_tb.v
`default_nettype none
`define DUMPSTR(x) `"x.vcd`"
`timescale 1ps / 10fs

module sync_generator_tb();

parameter DURATION = 10000000;

reg pixel_clk = 0;
reg rst = 0;
always #1 pixel_clk = ~pixel_clk;

wire [9:0] cycle;
wire [8:0] scanline;
wire vga_hs;
wire vga_vs;
wire vga_blank;

sync_generator uut (
    .pixel_clk(pixel_clk),
    .rst(rst),

    .cycle(cycle),
    .scanline(scanline),
    .vga_hs(vga_hs),
    .vga_vs(vga_vs),
    .vga_blank(vga_blank)
);

initial begin
    #0.1
    rst = 1'b0;
    #1
    rst = 1'b1;
end

initial begin
  $dumpfile(`DUMPSTR(`VCD_OUTPUT));
  $dumpvars(0, sync_generator_tb);

   #(DURATION) $display("End of simulation");
  $finish;
end

endmodule

verilog/gpu/pixel_generator.v
module pixel_generator (
    input rst,
    input pixel_clk,
    input clk,
    input [9:0] cycle,
    input [8:0] scanline,
    input [7:0] clk_read_data,

    output reg [12:0] clk_read_addr,
    output [7:0] pixel_data
);

reg [1:0] step;
reg [7:0] tileNumber;
reg [7:0] tileData;
reg [7:0] colorAttribute;
reg pixelOn;
reg [7:0] color;

wire [9:0] offsetCycle = ((cycle >> 1) + (0)) & 9'h1ff;
wire [8:0] offsetScanline = ((scanline >> 1) + (0)) & 8'hff;

wire [5:0] charColumn = offsetCycle >> 3;
wire [4:0] charRow = offsetCycle >> 3;

wire [2:0] charRenderColumn = offsetCycle & 3'h7;
wire [2:0] charRenderRow = offsetScanline & 3'h7;

// There will be 3 clk between each pixel_clk, use these clock cycles to fetch stuff from RAM
always @ (posedge clk or negedge rst) begin
    if(rst == 0) begin
        step <= 0;
        pixelOn <= 0;
        color <= 0;
    end else begin
        case (step)
            0: begin
                
                clk_read_addr = {2'b00, charRow, charColumn};
                tileNumber = clk_read_data;
                step = step + 1;
            end 
            1: begin
                clk_read_addr = {2'b10, charRenderRow + (tileNumber << 3)};
                tileData = clk_read_data;
                step = step + 1;
            end
            2: begin
                pixelOn = (tileData >> charRenderColumn) & 1;
                clk_read_addr = {2'b01, charRow, charColumn};
                colorAttribute = clk_read_data;
                step = step + 1;
            end
            3: begin
                if(pixelOn == 1) begin
                    clk_read_addr = 13'h1800 + colorAttribute[7:4];
                end else begin
                    clk_read_addr = 13'h1800 + colorAttribute[3:0];
                end

                color = clk_read_data;
                step = 0;
            end
        endcase
    end
end

assign pixel_data = color;

endmodule

verilog/gpu/clock_divider.v
module clock_divider #(
  parameter DIVISON = 2,
  parameter DIVISION_WIDTH = 2
)(
    input clk,
    input rst,

    output reg tick
);

reg [DIVISION_WIDTH:0] count;

always @(posedge clk or negedge rst) begin
    if (rst == 0) begin
        count <= 1'b0;
        tick <= 1'b0;
    end else if (count == DIVISON - 1) begin
        count <= 1'b0;
        tick <= ~tick;
    end else begin
        count <= count + 1'b1; 
    end
end

endmodule

verilog/gpu/pixel_generator_tb.v
`default_nettype none
`define DUMPSTR(x) `"x.vcd`"
`timescale 1ns / 10ps

module pixel_generator_tb();

parameter DURATION = 20;

wire pixel_clk = 0;
reg CLK100MHz = 0;
reg rst = 0;
wire [7:0] pixel_data;

reg [9:0] cycle;
reg [8:0] scanline;

wire [14:0] clk_read_addr;
wire [7:0] clk_read_data;

always #1 CLK100MHz = ~CLK100MHz;

clock_divider #(.DIVISON(2)) vga_div (
    .clk(CLK100MHz),
    .rst(rst),
    .tick(pixel_clk)
);

pixel_generator uut (
    .rst(rst),
    .pixel_clk(pixel_clk),
    .clk(CLK100MHz),
    .cycle(cycle),
    .scanline(scanline),

    .clk_read_addr(clk_read_addr),
    .clk_read_data(clk_read_data),

    .pixel_data(pixel_data)
);

initial begin
    #0.1 rst = 1'b0;
    cycle = 50;
    scanline = 2;
    #1 rst = 1'b1;
end

initial begin
  $dumpfile(`DUMPSTR(`VCD_OUTPUT));
  $dumpvars(0, pixel_generator_tb);

   #(DURATION) $display("End of simulation");
  $finish;
end

endmodule

verilog/gpu/memory.v
module memory #(
     parameter   INIT_FILE = "mem.txt"
) (
    input clk,
    input [12:0] clk_read_addr,
    
    output reg [7:0] clk_read_data
);

    reg [7:0] mem [0:7000];
    
    // Interact with the memory block
    always @ (posedge clk) begin
    
        // // Write to memory
        // if (w_en == 1'b1) begin
        //     mem[w_addr] <= w_data;
        // end
        
        // // Read from memory
        // if (r_en == 1'b1) begin
        //     r_data <= mem[r_addr];
        // end

        clk_read_data = mem[clk_read_addr];
    end

    initial if (INIT_FILE) begin
        $readmemh(INIT_FILE, mem);
    end

endmodule

verilog/gpu/gpu.v
module gpu (
    input CLK100MHz,
    input rst,
    input [7:0] data,
    input [3:0] addr,
    input rw,
    input cs_clock,

    output wire vga_hs,
    output wire vga_vs,
    output wire [2:0] vga_r,
    output wire [2:0] vga_g,
    output wire [2:0] vga_b,
    output wire irq
);

wire pixel_clk;
wire vga_blank;
wire [9:0] cycle;
wire [8:0] scanline;
wire [7:0] pixel_data;

wire [12:0] clk_read_addr;
wire [7:0] clk_read_data;

memory mem (
    .clk(CLK100MHz),
    .clk_read_addr(clk_read_addr),

    .clk_read_data(clk_read_data)
);

clock_divider #(.DIVISON(2)) vga_div (
    .clk(CLK100MHz),
    .rst(rst),
    .tick(pixel_clk)
);

sync_generator sync_gen (
    .pixel_clk(pixel_clk),
    .rst(rst),

    .cycle(cycle),
    .scanline(scanline),
    .vga_hs(vga_hs),
    .vga_vs(vga_vs),
    .vga_blank(vga_blank)
);

pixel_generator pixel_gen (
    .rst(rst),
    .pixel_clk(pixel_clk),
    .clk(CLK100MHz),
    .cycle(cycle),
    .scanline(scanline),

    .clk_read_addr(clk_read_addr),
    .clk_read_data(clk_read_data),

    .pixel_data(pixel_data)
);

assign vga_r = (vga_blank == 1) ? 0 : pixel_data[2:0]; 
assign vga_g = (vga_blank == 1) ? 0 : pixel_data[4:2]; 
assign vga_b = (vga_blank == 1) ? 0 : pixel_data[7:5]; 

endmodule

verilog/gpu/gpu_tb.v
`default_nettype none
`define DUMPSTR(x) `"x.vcd`"
`timescale 1ps / 10fs

module gpu_tb();

parameter DURATION = 10000000;

reg CLK100MHz = 0;
reg rst = 0;
always #1 CLK100MHz = ~CLK100MHz;

wire [7:0] data = 0;
wire [3:0] addr = 0;
wire rw = 0;
wire cs_clock = 1;

wire [2:0] vga_r;
wire [2:0] vga_g;
wire [2:0] vga_b;
wire irq;
wire vga_hs;
wire vga_vs;

gpu uut (
    .CLK100MHz(CLK100MHz),
    .rst(rst),
    .data(data),
    .addr(addr),
    .rw(rw),
    .cs_clock(cs_clock),

    .vga_hs(vga_hs),
    .vga_vs(vga_vs),
    .vga_r(vga_r),
    .vga_g(vga_g),
    .vga_b(vga_b),
    .irq(irq)
);

initial begin
    #0.1
    rst = 1'b0;
    #1
    rst = 1'b1;
end

initial begin
  $dumpfile(`DUMPSTR(`VCD_OUTPUT));
  $dumpvars(0, gpu_tb);

   #(DURATION) $display("End of simulation");
  $finish;
end

endmodule

verilog/gpu/clock_divider_tb.v
`default_nettype none
`define DUMPSTR(x) `"x.vcd`"
`timescale 100 ns / 10 ns

module clock_divider_tb();

parameter DURATION = 20;

reg clk = 0;
reg rst = 0;
always #0.5 clk = ~clk;

wire pixel_clk;

clock_divider #(.DIVISON(4), .DIVISION_WIDTH(3)) uut (
    .clk(clk),
    .rst(rst),
    .tick(pixel_clk)
);

initial begin
    #0.1
    rst = 1'b0;
    #1
    rst = 1'b1;
end

initial begin
  $dumpfile(`DUMPSTR(`VCD_OUTPUT));
  $dumpvars(0, clock_divider_tb);

   #(DURATION) $display("End of simulation");
  $finish;
end

endmodule

verilog/gpu/clock_divider_tb.vcd
$date
	Thu Dec 15 10:10:50 2022
$end
$version
	Icarus Verilog
$end
$timescale
	10fs
$end
$scope module clock_divider_tb $end
$var wire 1 ! pixel_clk $end
$var reg 1 " clk $end
$var reg 1 # rst $end
$scope module uut $end
$var wire 1 " clk $end
$var wire 1 # rst $end
$var reg 4 $ count [3:0] $end
$var reg 1 ! tick $end
$upscope $end
$upscope $end
$scope module gpu_tb $end
$var wire 4 % addr [3:0] $end
$var wire 1 & cs_clock $end
$var wire 8 ' data [7:0] $end
$var wire 1 ( irq $end
$var wire 1 ) rw $end
$var wire 1 * vga_vs $end
$var wire 3 + vga_r [2:0] $end
$var wire 1 , vga_hs $end
$var wire 3 - vga_g [2:0] $end
$var wire 3 . vga_b [2:0] $end
$var reg 1 / CLK100MHz $end
$var reg 1 0 rst $end
$scope module uut $end
$var wire 1 / CLK100MHz $end
$var wire 4 1 addr [3:0] $end
$var wire 1 & cs_clock $end
$var wire 8 2 data [7:0] $end
$var wire 1 ( irq $end
$var wire 1 0 rst $end
$var wire 1 ) rw $end
$var wire 1 * vga_vs $end
$var wire 3 3 vga_r [2:0] $end
$var wire 1 , vga_hs $end
$var wire 3 4 vga_g [2:0] $end
$var wire 1 5 vga_blank $end
$var wire 3 6 vga_b [2:0] $end
$var wire 9 7 scanline [8:0] $end
$var wire 8 8 pixel_data [7:0] $end
$var wire 1 9 pixel_clk $end
$var wire 10 : cycle [9:0] $end
$var wire 8 ; clk_read_data [7:0] $end
$var wire 13 < clk_read_addr [12:0] $end
$scope module mem $end
$var wire 1 / clk $end
$var wire 13 = clk_read_addr [12:0] $end
$var reg 8 > clk_read_data [7:0] $end
$upscope $end
$scope module pixel_gen $end
$var wire 1 / clk $end
$var wire 8 ? clk_read_data [7:0] $end
$var wire 8 @ pixel_data [7:0] $end
$var wire 1 0 rst $end
$var wire 9 A scanline [8:0] $end
$var wire 1 9 pixel_clk $end
$var wire 9 B offsetScanline [8:0] $end
$var wire 10 C offsetCycle [9:0] $end
$var wire 10 D cycle [9:0] $end
$var wire 5 E charRow [4:0] $end
$var wire 3 F charRenderRow [2:0] $end
$var wire 3 G charRenderColumn [2:0] $end
$var wire 6 H charColumn [5:0] $end
$var reg 13 I clk_read_addr [12:0] $end
$var reg 8 J color [7:0] $end
$var reg 8 K colorAttribute [7:0] $end
$var reg 1 L pixelOn $end
$var reg 2 M step [1:0] $end
$var reg 8 N tileData [7:0] $end
$var reg 8 O tileNumber [7:0] $end
$upscope $end
$scope module sync_gen $end
$var wire 1 0 rst $end
$var wire 1 , vga_hs $end
$var wire 1 * vga_vs $end
$var wire 1 9 pixel_clk $end
$var reg 10 P cycle [9:0] $end
$var reg 9 Q scanline [8:0] $end
$var reg 1 5 vga_blank $end
$upscope $end
$scope module vga_div $end
$var wire 1 / clk $end
$var wire 1 0 rst $end
$var reg 3 R count [2:0] $end
$var reg 1 9 tick $end
$upscope $end
$upscope $end
$upscope $end
$scope module pixel_generator_tb $end
$var wire 8 S clk_read_data [7:0] $end
$var wire 1 T pixel_clk $end
$var wire 8 U pixel_data [7:0] $end
$var wire 15 V clk_read_addr [14:0] $end
$var reg 1 W CLK100MHz $end
$var reg 10 X cycle [9:0] $end
$var reg 1 Y rst $end
$var reg 9 Z scanline [8:0] $end
$scope module uut $end
$var wire 1 W clk $end
$var wire 8 [ clk_read_data [7:0] $end
$var wire 10 \ cycle [9:0] $end
$var wire 1 T pixel_clk $end
$var wire 8 ] pixel_data [7:0] $end
$var wire 1 Y rst $end
$var wire 9 ^ scanline [8:0] $end
$var wire 9 _ offsetScanline [8:0] $end
$var wire 10 ` offsetCycle [9:0] $end
$var wire 5 a charRow [4:0] $end
$var wire 3 b charRenderRow [2:0] $end
$var wire 3 c charRenderColumn [2:0] $end
$var wire 6 d charColumn [5:0] $end
$var reg 13 e clk_read_addr [12:0] $end
$var reg 8 f color [7:0] $end
$var reg 8 g colorAttribute [7:0] $end
$var reg 1 h pixelOn $end
$var reg 2 i step [1:0] $end
$var reg 8 j tileData [7:0] $end
$var reg 8 k tileNumber [7:0] $end
$upscope $end
$scope module vga_div $end
$var wire 1 W clk $end
$var wire 1 Y rst $end
$var reg 3 l count [2:0] $end
$var reg 1 m tick $end
$upscope $end
$upscope $end
$scope module sync_generator_tb $end
$var wire 1 n vga_vs $end
$var wire 1 o vga_hs $end
$var wire 1 p vga_blank $end
$var wire 9 q scanline [8:0] $end
$var wire 10 r cycle [9:0] $end
$var reg 1 s pixel_clk $end
$var reg 1 t rst $end
$scope module uut $end
$var wire 1 s pixel_clk $end
$var wire 1 t rst $end
$var wire 1 o vga_hs $end
$var wire 1 n vga_vs $end
$var reg 10 u cycle [9:0] $end
$var reg 9 v scanline [8:0] $end
$var reg 1 p vga_blank $end
$upscope $end
$upscope $end
$enddefinitions $end
#0
$dumpvars
b0 v
b0 u
0t
0s
b0 r
b0 q
xp
1o
1n
0m
b0 l
bx k
bx j
b0 i
0h
bx g
b0 f
bx e
bx d
bx c
bx b
bx a
b0xxxxxxxxx `
b0xxxxxxxx _
bx ^
b0 ]
bx \
bz [
bx Z
0Y
bx X
0W
b0xxxxxxxxxxxxx V
b0 U
0T
bz S
b0 R
b0 Q
b0 P
bx O
bx N
b0 M
0L
bx K
b0 J
bx I
b0 H
b0 G
b0 F
b0 E
b0 D
b0 C
b0 B
b0 A
b0 @
bx ?
bx >
bx =
bx <
bx ;
b0 :
09
b0 8
b0 7
b0 6
x5
b0 4
b0 3
b0 2
b0 1
00
0/
b0 .
b0 -
1,
b0 +
1*
0)
z(
b0 '
1&
b0 %
b0 $
0#
0"
0!
$end
#100
1s
1/
#110
1t
10
#200
0s
0/
#300
b1 R
0p
b1 r
b1 u
b0 ;
b0 >
b0 ?
b1 M
b0 <
b0 =
b0 I
1s
1/
#400
0s
0/
#500
05
b1 :
b1 D
b1 P
19
b0 R
b10 r
b10 u
bx ;
bx >
bx ?
b10 M
b0 N
b10xxxxxxxx <
b10xxxxxxxx =
b10xxxxxxxx I
1s
1/
#600
0s
0/
#700
b1 R
b11 r
b11 u
b100010 ;
b100010 >
b100010 ?
b11 M
b100000000000 <
b100000000000 =
b100000000000 I
1s
1/
#800
0s
0/
#900
09
b0 R
b1 .
b1 6
b10 +
b10 3
b100 r
b100 u
bx ;
bx >
bx ?
b0 M
b100010 8
b100010 @
b100010 J
bx <
bx =
bx I
1s
1/
#1000
0s
0/
#1100
b1 R
b101 r
b101 u
b0 ;
b0 >
b0 ?
b1 M
b0 <
b0 =
b0 I
1s
1/
#1200
0s
0/
#1300
b1 G
b1 C
b10 :
b10 D
b10 P
19
b0 R
b110 r
b110 u
bx ;
bx >
bx ?
b10 M
b10xxxxxxxx <
b10xxxxxxxx =
b10xxxxxxxx I
1s
1/
#1400
0s
0/
#1500
b1 R
b111 r
b111 u
b100010 ;
b100010 >
b100010 ?
b11 M
b100000000000 <
b100000000000 =
b100000000000 I
1s
1/
#1600
0s
0/
#1700
09
b0 R
b1000 r
b1000 u
bx ;
bx >
bx ?
b0 M
bx <
bx =
bx I
1s
1/
#1800
0s
0/
#1900
b1 R
b1001 r
b1001 u
b0 ;
b0 >
b0 ?
b1 M
b0 <
b0 =
b0 I
1s
1/
#2000
0s
0/
#2100
b11 :
b11 D
b11 P
19
b0 R
b1010 r
b1010 u
bx ;
bx >
bx ?
b10 M
b10xxxxxxxx <
b10xxxxxxxx =
b10xxxxxxxx I
1s
1/
#2200
0s
0/
#2300
b1 R
b1011 r
b1011 u
b100010 ;
b100010 >
b100010 ?
b11 M
b100000000000 <
b100000000000 =
b100000000000 I
1s
1/
#2400
0s
0/
#2500
09
b0 R
b1100 r
b1100 u
bx ;
bx >
bx ?
b0 M
bx <
bx =
bx I
1s
1/
#2600
0s
0/
#2700
b1 R
b1101 r
b1101 u
b0 ;
b0 >
b0 ?
b1 M
b0 <
b0 =
b0 I
1s
1/
#2800
0s
0/
#2900
b10 G
b10 C
b100 :
b100 D
b100 P
19
b0 R
b1110 r
b1110 u
bx ;
bx >
bx ?
b10 M
b10xxxxxxxx <
b10xxxxxxxx =
b10xxxxxxxx I
1s
1/
#3000
0s
0/
#3100
b1 R
b1111 r
b1111 u
b100010 ;
b100010 >
b100010 ?
b11 M
b100000000000 <
b100000000000 =
b100000000000 I
1s
1/
#3200
0s
0/
#3300
09
b0 R
b10000 r
b10000 u
bx ;
bx >
bx ?
b0 M
bx <
bx =
bx I
1s
1/
#3400
0s
0/
#3500
b1 R
b10001 r
b10001 u
b0 ;
b0 >
b0 ?
b1 M
b0 <
b0 =
b0 I
1s
1/
#3600
0s
0/
#3700
b101 :
b101 D
b101 P
19
b0 R
b10010 r
b10010 u
bx ;
bx >
bx ?
b10 M
b10xxxxxxxx <
b10xxxxxxxx =
b10xxxxxxxx I
1s
1/
#3800
0s
0/
#3900
b1 R
b10011 r
b10011 u
b100010 ;
b100010 >
b100010 ?
b11 M
b100000000000 <
b100000000000 =
b100000000000 I
1s
1/
#4000
0s
0/
#4100
09
b0 R
b10100 r
b10100 u
bx ;
bx >
bx ?
b0 M
bx <
bx =
bx I
1s
1/
#4200
0s
0/
#4300
b1 R
b10101 r
b10101 u
b0 ;
b0 >
b0 ?
b1 M
b0 <
b0 =
b0 I
1s
1/
#4400
0s
0/
#4500
b11 G
b11 C
b110 :
b110 D
b110 P
19
b0 R
b10110 r
b10110 u
bx ;
bx >
bx ?
b10 M
b10xxxxxxxx <
b10xxxxxxxx =
b10xxxxxxxx I
1s
1/
#4600
0s
0/
#4700
b1 R
b10111 r
b10111 u
b100010 ;
b100010 >
b100010 ?
b11 M
b100000000000 <
b100000000000 =
b100000000000 I
1s
1/
#4800
0s
0/
#4900
09
b0 R
b11000 r
b11000 u
bx ;
bx >
bx ?
b0 M
bx <
bx =
bx I
1s
1/
#5000
0s
0/
#5100
b1 R
b11001 r
b11001 u
b0 ;
b0 >
b0 ?
b1 M
b0 <
b0 =
b0 I
1s
1/
#5200
0s
0/
#5300
b111 :
b111 D
b111 P
19
b0 R
b11010 r
b11010 u
bx ;
bx >
bx ?
b10 M
b10xxxxxxxx <
b10xxxxxxxx =
b10xxxxxxxx I
1s
1/
#5400
0s
0/
#5500
b1 R
b11011 r
b11011 u
b100010 ;
b100010 >
b100010 ?
b11 M
b100000000000 <
b100000000000 =
b100000000000 I
1s
1/
#5600
0s
0/
#5700
09
b0 R
b11100 r
b11100 u
bx ;
bx >
bx ?
b0 M
bx <
bx =
bx I
1s
1/
#5800
0s
0/
#5900
b1 R
b11101 r
b11101 u
b0 ;
b0 >
b0 ?
b1 M
b0 <
b0 =
b0 I
1s
1/
#6000
0s
0/
#6100
b100 G
b100 C
b1000 :
b1000 D
b1000 P
19
b0 R
b11110 r
b11110 u
bx ;
bx >
bx ?
b10 M
b10xxxxxxxx <
b10xxxxxxxx =
b10xxxxxxxx I
1s
1/
#6200
0s
0/
#6300
b1 R
b11111 r
b11111 u
b100010 ;
b100010 >
b100010 ?
b11 M
b100000000000 <
b100000000000 =
b100000000000 I
1s
1/
#6400
0s
0/
#6500
09
b0 R
b100000 r
b100000 u
bx ;
bx >
bx ?
b0 M
bx <
bx =
bx I
1s
1/
#6600
0s
0/
#6700
b1 R
b100001 r
b100001 u
b0 ;
b0 >
b0 ?
b1 M
b0 <
b0 =
b0 I
1s
1/
#6800
0s
0/
#6900
b1001 :
b1001 D
b1001 P
19
b0 R
b100010 r
b100010 u
bx ;
bx >
bx ?
b10 M
b10xxxxxxxx <
b10xxxxxxxx =
b10xxxxxxxx I
1s
1/
#7000
0s
0/
#7100
b1 R
b100011 r
b100011 u
b100010 ;
b100010 >
b100010 ?
b11 M
b100000000000 <
b100000000000 =
b100000000000 I
1s
1/
#7200
0s
0/
#7300
09
b0 R
b100100 r
b100100 u
bx ;
bx >
bx ?
b0 M
bx <
bx =
bx I
1s
1/
#7400
0s
0/
#7500
b1 R
b100101 r
b100101 u
b0 ;
b0 >
b0 ?
b1 M
b0 <
b0 =
b0 I
1s
1/
#7600
0s
0/
#7700
b101 G
b101 C
b1010 :
b1010 D
b1010 P
19
b0 R
b100110 r
b100110 u
bx ;
bx >
bx ?
b10 M
b10xxxxxxxx <
b10xxxxxxxx =
b10xxxxxxxx I
1s
1/
#7800
0s
0/
#7900
b1 R
b100111 r
b100111 u
b100010 ;
b100010 >
b100010 ?
b11 M
b100000000000 <
b100000000000 =
b100000000000 I
1s
1/
#8000
0s
0/
#8100
09
b0 R
b101000 r
b101000 u
bx ;
bx >
bx ?
b0 M
bx <
bx =
bx I
1s
1/
#8200
0s
0/
#8300
b1 R
b101001 r
b101001 u
b0 ;
b0 >
b0 ?
b1 M
b0 <
b0 =
b0 I
1s
1/
#8400
0s
0/
#8500
b1011 :
b1011 D
b1011 P
19
b0 R
b101010 r
b101010 u
bx ;
bx >
bx ?
b10 M
b10xxxxxxxx <
b10xxxxxxxx =
b10xxxxxxxx I
1s
1/
#8600
0s
0/
#8700
b1 R
b101011 r
b101011 u
b100010 ;
b100010 >
b100010 ?
b11 M
b100000000000 <
b100000000000 =
b100000000000 I
1s
1/
#8800
0s
0/
#8900
09
b0 R
b101100 r
b101100 u
bx ;
bx >
bx ?
b0 M
bx <
bx =
bx I
1s
1/
#9000
0s
0/
#9100
b1 R
b101101 r
b101101 u
b0 ;
b0 >
b0 ?
b1 M
b0 <
b0 =
b0 I
1s
1/
#9200
0s
0/
#9300
b110 G
b110 C
b1100 :
b1100 D
b1100 P
19
b0 R
b101110 r
b101110 u
bx ;
bx >
bx ?
b10 M
b10xxxxxxxx <
b10xxxxxxxx =
b10xxxxxxxx I
1s
1/
#9400
0s
0/
#9500
b1 R
b101111 r
b101111 u
b100010 ;
b100010 >
b100010 ?
b11 M
b100000000000 <
b100000000000 =
b100000000000 I
1s
1/
#9600
0s
0/
#9700
09
b0 R
b110000 r
b110000 u
bx ;
bx >
bx ?
b0 M
bx <
bx =
bx I
1s
1/
#9800
0s
0/
#9900
b1 R
b110001 r
b110001 u
b0 ;
b0 >
b0 ?
b1 M
b0 <
b0 =
b0 I
1s
1/
#10000
b1 b
b11 d
b11 a
b1 c
b1 _
b11001 `
0s
0/
b10 Z
b10 ^
b110010 X
b110010 \
#10100
b1101 :
b1101 D
b1101 P
19
b0 R
b110010 r
b110010 u
bx ;
bx >
bx ?
b10 M
b10xxxxxxxx <
b10xxxxxxxx =
b10xxxxxxxx I
1s
1/
#10200
0s
0/
#10300
b1 R
b110011 r
b110011 u
b100010 ;
b100010 >
b100010 ?
b11 M
b100000000000 <
b100000000000 =
b100000000000 I
1s
1/
#10400
0s
0/
#10500
09
b0 R
b110100 r
b110100 u
bx ;
bx >
bx ?
b0 M
bx <
bx =
bx I
1s
1/
#10600
0s
0/
#10700
b1 R
b110101 r
b110101 u
b0 ;
b0 >
b0 ?
b1 M
b0 <
b0 =
b0 I
1s
1/
#10800
0s
0/
#10900
b111 G
b111 C
b1110 :
b1110 D
b1110 P
19
b0 R
b110110 r
b110110 u
bx ;
bx >
bx ?
b10 M
b10xxxxxxxx <
b10xxxxxxxx =
b10xxxxxxxx I
1s
1/
#11000
0s
0/
#11100
b1 R
b110111 r
b110111 u
b100010 ;
b100010 >
b100010 ?
b11 M
b100000000000 <
b100000000000 =
b100000000000 I
1s
1/
#11200
0s
0/
#11300
09
b0 R
b111000 r
b111000 u
bx ;
bx >
bx ?
b0 M
bx <
bx =
bx I
1s
1/
#11400
0s
0/
#11500
b1 R
b111001 r
b111001 u
b0 ;
b0 >
b0 ?
b1 M
b0 <
b0 =
b0 I
1s
1/
#11600
0s
0/
#11700
b1111 :
b1111 D
b1111 P
19
b0 R
b111010 r
b111010 u
bx ;
bx >
bx ?
b10 M
b10xxxxxxxx <
b10xxxxxxxx =
b10xxxxxxxx I
1s
1/
#11800
0s
0/
#11900
b1 R
b111011 r
b111011 u
b100010 ;
b100010 >
b100010 ?
b11 M
b100000000000 <
b100000000000 =
b100000000000 I
1s
1/
#12000
0s
0/
#12100
09
b0 R
b111100 r
b111100 u
bx ;
bx >
bx ?
b0 M
bx <
bx =
bx I
1s
1/
#12200
0s
0/
#12300
b1 R
b111101 r
b111101 u
b0 ;
b0 >
b0 ?
b1 M
b0 <
b0 =
b0 I
1s
1/
#12400
0s
0/
#12500
b1 H
b1 E
b0 G
b1000 C
b10000 :
b10000 D
b10000 P
19
b0 R
b111110 r
b111110 u
bx ;
bx >
bx ?
b10 M
b10xxxxxxxx <
b10xxxxxxxx =
b10xxxxxxxx I
1s
1/
#12600
0s
0/
#12700
b1 R
b111111 r
b111111 u
b100010 ;
b100010 >
b100010 ?
b11 M
b100001000001 <
b100001000001 =
b100001000001 I
1s
1/
#12800
0s
0/
#12900
09
b0 R
b1000000 r
b1000000 u
bx ;
bx >
bx ?
b0 M
bx <
bx =
bx I
1s
1/
#13000
0s
0/
#13100
b1 R
b1000001 r
b1000001 u
b0 ;
b0 >
b0 ?
b1 M
b1000001 <
b1000001 =
b1000001 I
1s
1/
#13200
0s
0/
#13300
b10001 :
b10001 D
b10001 P
19
b0 R
b1000010 r
b1000010 u
bx ;
bx >
bx ?
b10 M
b10xxxxxxxx <
b10xxxxxxxx =
b10xxxxxxxx I
1s
1/
#13400
0s
0/
#13500
b1 R
b1000011 r
b1000011 u
b100010 ;
b100010 >
b100010 ?
b11 M
b100001000001 <
b100001000001 =
b100001000001 I
1s
1/
#13600
0s
0/
#13700
09
b0 R
b1000100 r
b1000100 u
bx ;
bx >
bx ?
b0 M
bx <
bx =
bx I
1s
1/
#13800
0s
0/
#13900
b1 R
b1000101 r
b1000101 u
b0 ;
b0 >
b0 ?
b1 M
b1000001 <
b1000001 =
b1000001 I
1s
1/
#14000
0s
0/
#14100
b1 G
b1001 C
b10010 :
b10010 D
b10010 P
19
b0 R
b1000110 r
b1000110 u
bx ;
bx >
bx ?
b10 M
b10xxxxxxxx <
b10xxxxxxxx =
b10xxxxxxxx I
1s
1/
#14200
0s
0/
#14300
b1 R
b1000111 r
b1000111 u
b100010 ;
b100010 >
b100010 ?
b11 M
b100001000001 <
b100001000001 =
b100001000001 I
1s
1/
#14400
0s
0/
#14500
09
b0 R
b1001000 r
b1001000 u
bx ;
bx >
bx ?
b0 M
bx <
bx =
bx I
1s
1/
#14600
0s
0/
#14700
b1 R
b1001001 r
b1001001 u
b0 ;
b0 >
b0 ?
b1 M
b1000001 <
b1000001 =
b1000001 I
1s
1/
#14800
0s
0/
#14900
b10011 :
b10011 D
b10011 P
19
b0 R
b1001010 r
b1001010 u
bx ;
bx >
bx ?
b10 M
b10xxxxxxxx <
b10xxxxxxxx =
b10xxxxxxxx I
1s
1/
#15000
0s
0/
#15100
b1 R
b1001011 r
b1001011 u
b100010 ;
b100010 >
b100010 ?
b11 M
b100001000001 <
b100001000001 =
b100001000001 I
1s
1/
#15200
0s
0/
#15300
09
b0 R
b1001100 r
b1001100 u
bx ;
bx >
bx ?
b0 M
bx <
bx =
bx I
1s
1/
#15400
0s
0/
#15500
b1 R
b1001101 r
b1001101 u
b0 ;
b0 >
b0 ?
b1 M
b1000001 <
b1000001 =
b1000001 I
1s
1/
#15600
0s
0/
#15700
b10 G
b1010 C
b10100 :
b10100 D
b10100 P
19
b0 R
b1001110 r
b1001110 u
bx ;
bx >
bx ?
b10 M
b10xxxxxxxx <
b10xxxxxxxx =
b10xxxxxxxx I
1s
1/
#15800
0s
0/
#15900
b1 R
b1001111 r
b1001111 u
b100010 ;
b100010 >
b100010 ?
b11 M
b100001000001 <
b100001000001 =
b100001000001 I
1s
1/
#16000
0s
0/
#16100
09
b0 R
b1010000 r
b1010000 u
bx ;
bx >
bx ?
b0 M
bx <
bx =
bx I
1s
1/
#16200
0s
0/
#16300
b1 R
b1010001 r
b1010001 u
b0 ;
b0 >
b0 ?
b1 M
b1000001 <
b1000001 =
b1000001 I
1s
1/
#16400
0s
0/
#16500
b10101 :
b10101 D
b10101 P
19
b0 R
b1010010 r
b1010010 u
bx ;
bx >
bx ?
b10 M
b10xxxxxxxx <
b10xxxxxxxx =
b10xxxxxxxx I
1s
1/
#16600
0s
0/
#16700
b1 R
b1010011 r
b1010011 u
b100010 ;
b100010 >
b100010 ?
b11 M
b100001000001 <
b100001000001 =
b100001000001 I
1s
1/
#16800
0s
0/
#16900
09
b0 R
b1010100 r
b1010100 u
bx ;
bx >
bx ?
b0 M
bx <
bx =
bx I
1s
1/
#17000
0s
0/
#17100
b1 R
b1010101 r
b1010101 u
b0 ;
b0 >
b0 ?
b1 M
b1000001 <
b1000001 =
b1000001 I
1s
1/
#17200
0s
0/
#17300
b11 G
b1011 C
b10110 :
b10110 D
b10110 P
19
b0 R
b1010110 r
b1010110 u
bx ;
bx >
bx ?
b10 M
b10xxxxxxxx <
b10xxxxxxxx =
b10xxxxxxxx I
1s
1/
#17400
0s
0/
#17500
b1 R
b1010111 r
b1010111 u
b100010 ;
b100010 >
b100010 ?
b11 M
b100001000001 <
b100001000001 =
b100001000001 I
1s
1/
#17600
0s
0/
#17700
09
b0 R
b1011000 r
b1011000 u
bx ;
bx >
bx ?
b0 M
bx <
bx =
bx I
1s
1/
#17800
0s
0/
#17900
b1 R
b1011001 r
b1011001 u
b0 ;
b0 >
b0 ?
b1 M
b1000001 <
b1000001 =
b1000001 I
1s
1/
#18000
0s
0/
